lokstats/__init__.py
lokstats/adv_cor.py
lokstats/test.py
lokstats-0.0.1.dist-info/LICENSE.txt
lokstats-0.0.1.dist-info/METADATA
lokstats-0.0.1.dist-info/WHEEL
lokstats-0.0.1.dist-info/top_level.txt
lokstats-0.0.1.dist-info/RECORD
