Metadata-Version: 2.1
Name: lokstats
Version: 0.0.1
Summary: it is for advanced statistics calculations of partial and multiple correlations
Home-page: https://github.com/loksundar/partial_multiple_correlation
Author: LOK SUNDAR GANTHI
Author-email: loksundar000@gmail.com
License: UNKNOWN
Platform: UNKNOWN
Classifier: Programming Language :: Python :: 3
Classifier: License :: OSI Approved :: MIT License
Classifier: Operating System :: OS Independent
Requires-Python: >=3.6
